audiotagger/__init__.py
audiotagger/api/__init__.py
audiotagger/api/api.py
audiotagger/api/main.py
audiotagger/core/__init__.py
audiotagger/core/audiotagger.py
audiotagger/core/clear_tags.py
audiotagger/core/copy_file.py
audiotagger/core/create_playlist.py
audiotagger/core/paths.py
audiotagger/data/__init__.py
audiotagger/data/base_io.py
audiotagger/data/fields.py
audiotagger/data/input.py
audiotagger/data/loader.py
audiotagger/data/output.py
audiotagger/modifier/__init__.py
audiotagger/modifier/audiotagger_modifier.py
audiotagger/settings/__init__.py
audiotagger/settings/settings.py
audiotagger/tests/__init__.py
audiotagger/tests/test_file_util.py
audiotagger/tests/data/__init__.py
audiotagger/tests/data/test_input.py
audiotagger/tests/data/test_loader.py
audiotagger/util/__init__.py
audiotagger/util/audiotagger_setup.py
audiotagger/util/file_util.py
audiotagger/util/input_output_util.py
audiotagger/util/tag_util.py
audiotagger-0.0.0.dist-info/LICENSE
audiotagger-0.0.0.dist-info/METADATA
audiotagger-0.0.0.dist-info/WHEEL
audiotagger-0.0.0.dist-info/top_level.txt
audiotagger-0.0.0.dist-info/RECORD
