Metadata-Version: 2.1
Name: audiotagger
Version: 0.0.0
Summary: Cross-platform metadata editor for audio files.
Home-page: https://github.com/vincentzhchen/audiotagger
Author: Vincent Chen
Author-email: vincent.zh.chen@gmail.com
License: GPL-3.0-or-later
Project-URL: Source, https://github.com/vincentzhchen/audiotagger
Platform: UNKNOWN
Classifier: License :: OSI Approved :: GNU General Public License v3 or later (GPLv3+)
Classifier: Development Status :: 4 - Beta
Classifier: Programming Language :: Python :: 3.6
Classifier: Programming Language :: Python :: 3.7
Classifier: Topic :: System :: Logging
Requires-Python: >=3.6
Requires-Dist: pandas (<0.24.0,>=0.18.0)
Requires-Dist: mutagen (>=1.41.1)
Requires-Dist: redquill
